pvpy/ASTMG173.csv
pvpy/PowerSpectrum.py
pvpy/SolarCell.py
pvpy/__init__.py
pvpy/lsc.py
pvpy-1.4.1a0.dist-info/METADATA
pvpy-1.4.1a0.dist-info/RECORD
pvpy-1.4.1a0.dist-info/WHEEL
pvpy-1.4.1a0.dist-info/top_level.txt
solspec/ASTMG173.csv
solspec/PowerSpectrum.py
solspec/__init__.py
