Metadata-Version: 2.1
Name: pvpy
Version: 1.4.1a0
Summary: Some routines relating photovoltaic solar cells
Home-page: https://github.com/soamaven/pvpy
Author: Colton Bukowsky
Author-email: cb@caltech.edu
License: MIT
Download-URL: https://github.com/soamaven/pvpy/tarball/1.0.alpha
Keywords: solar,photovoltaics,shockley,queisser,yablonovitch,short-circuit current,open-circuit voltage
Platform: UNKNOWN
Classifier: Development Status :: 3 - Alpha
Classifier: License :: OSI Approved :: MIT License
Classifier: Programming Language :: Python :: 2.7
Classifier: Programming Language :: Python :: 2.7
Classifier: Programming Language :: Python :: 3
Classifier: Programming Language :: Python :: 3.5
Classifier: Programming Language :: Python :: 3.6
Classifier: Programming Language :: Python :: 3.7
Classifier: Topic :: Scientific/Engineering :: Physics
Requires-Dist: numpy
Requires-Dist: scipy
